teamzones/__main__.py
teamzones/app.py
teamzones/inputs.py
teamzones/time_format.py
teamzones/time_format_test.py
teamzones-1.0.1.dist-info/LICENCE
teamzones-1.0.1.dist-info/METADATA
teamzones-1.0.1.dist-info/WHEEL
teamzones-1.0.1.dist-info/entry_points.txt
teamzones-1.0.1.dist-info/RECORD
