Metadata-Version: 2.3
Name: teamzones
Version: 1.0.1
Summary: 
License: MIT
Author: Paul Chiu
Author-email: paulchiu@gmail.com
Requires-Python: >=3.13
Classifier: License :: OSI Approved :: MIT License
Classifier: Programming Language :: Python :: 3
Classifier: Programming Language :: Python :: 3.13
Requires-Dist: python-dateutil (>=2.9.0.post0,<3.0.0)
Requires-Dist: typer (>=0.15.1,<0.16.0)
